KKRtoVAMPIRE/Converter.py
KKRtoVAMPIRE/__init__.py
KKRtoVAMPIRE/plot_UCF_JvsR.py
KKRtoVAMPIRE/utils.py
KKRtoVAMPIRE-0.1.13.dist-info/LICENSE
KKRtoVAMPIRE-0.1.13.dist-info/METADATA
KKRtoVAMPIRE-0.1.13.dist-info/WHEEL
KKRtoVAMPIRE-0.1.13.dist-info/top_level.txt
KKRtoVAMPIRE-0.1.13.dist-info/RECORD
