Metadata-Version: 2.1
Name: KKRtoVAMPIRE
Version: 0.1.13
Summary: Convert SPR-KKR Heisenberg model to VAMPIRE format
Author: L. Vojacek
Author-email: Libor.Vojacek@vutbr.cz
License: BSD 3-Clause License
License-File: LICENSE
Requires-Dist: numpy
Requires-Dist: matplotlib
Requires-Dist: scipy
Requires-Dist: pytest
Requires-Dist: pytest-cov
Requires-Dist: pytest-mpl
